{
  "_class": "text",
  "attributedString": {
    "_class": "attributedString",
    "attributes": [
      {
        "_class": "stringAttribute",
        "attributes": {
          "MSAttributedStringColorAttribute": {
            "_class": "color",
            "alpha": 1,
            "blue": 0.886238694190979,
            "green": 0.5645518898963928,
            "red": 0.288655698299408
          },
          "MSAttributedStringFontAttribute": {
            "_class": "fontDescriptor",
            "attributes": {
              "name": "OpenSans",
              "size": 12
            }
          },
          "kerning": 0,
          "paragraphStyle": {
            "_class": "paragraphStyle",
            "alignment": 1,
            "allowsDefaultTighteningForTruncation": 0
          }
        },
        "length": 4,
        "location": 0
      }
    ],
    "string": "Edit"
  },
  "automaticallyDrawOnUnderlyingPath": false,
  "do_objectID": "02ABE849-BA66-47F2-86DD-ED61497C0062",
  "dontSynchroniseWithSymbol": false,
  "exportOptions": {
    "_class": "exportOptions",
    "do_objectID": "18BAB314-3E70-40F1-BF47-6BF28398818E",
    "exportFormats": [
    ],
    "includedLayerIds": [
    ],
    "layerOptions": 0,
    "shouldTrim": false
  },
  "frame": {
    "_class": "rect",
    "constrainProportions": false,
    "do_objectID": "DBABFAB1-E4E3-4FAA-AC7A-4769EFE6864D",
    "height": 17,
    "width": 114.9999999999999,
    "x": 165,
    "y": 12
  },
  "glyphBounds": "{{94, 3}, {21, 11}}",
  "isFlippedHorizontal": false,
  "isFlippedVertical": false,
  "isLocked": false,
  "isVisible": true,
  "layerListExpandedType": 0,
  "lineSpacingBehaviour": 2,
  "name": "Edit",
  "nameIsFixed": false,
  "resizingConstraint": 12,
  "resizingType": 0,
  "rotation": 0,
  "shouldBreakMaskChain": false,
  "style": {
    "_class": "style",
    "do_objectID": "717A1D02-0C66-4347-9D75-05F8BBE97ED5",
    "endDecorationType": 0,
    "miterLimit": 10,
    "startDecorationType": 0,
    "textStyle": {
      "_class": "textStyle",
      "do_objectID": "3948E9CD-060B-46C1-94B9-C7C9D6973AF8",
      "encodedAttributes": {
        "MSAttributedStringColorAttribute": {
          "_class": "color",
          "alpha": 1,
          "blue": 0.886238694190979,
          "green": 0.5645518898963928,
          "red": 0.288655698299408
        },
        "MSAttributedStringFontAttribute": {
          "_class": "fontDescriptor",
          "attributes": {
            "name": "OpenSans",
            "size": 12
          }
        },
        "kerning": 0,
        "paragraphStyle": {
          "_class": "paragraphStyle",
          "alignment": 1,
          "allowsDefaultTighteningForTruncation": 0
        }
      },
      "verticalAlignment": 0
    }
  },
  "textBehaviour": 1
}