{
  "_class": "shapePath",
  "booleanOperation": 1,
  "do_objectID": "56744B1F-106E-4800-B712-FE09A516184E",
  "edited": true,
  "exportOptions": {
    "_class": "exportOptions",
    "exportFormats": [
    ],
    "includedLayerIds": [
    ],
    "layerOptions": 0,
    "shouldTrim": false
  },
  "frame": {
    "_class": "rect",
    "constrainProportions": false,
    "height": 12.08432364904621,
    "width": 12.08432364904621,
    "x": 7.960679809463643,
    "y": 7.954830669265653
  },
  "isClosed": true,
  "isFlippedHorizontal": false,
  "isFlippedVertical": false,
  "isLocked": false,
  "isVisible": true,
  "layerListExpandedType": 0,
  "name": "Path",
  "nameIsFixed": false,
  "pointRadiusBehaviour": 1,
  "points": [
    {
      "_class": "curvePoint",
      "cornerRadius": 0,
      "curveFrom": "{0.22410454985479175, 0}",
      "curveMode": 2,
      "curveTo": "{0.77589545014520778, 0}",
      "hasCurveFrom": true,
      "hasCurveTo": true,
      "point": "{0.49999999999999989, 0}"
    },
    {
      "_class": "curvePoint",
      "cornerRadius": 0,
      "curveFrom": "{0, 0.77589545014520811}",
      "curveMode": 2,
      "curveTo": "{0, 0.22410454985479178}",
      "hasCurveFrom": true,
      "hasCurveTo": true,
      "point": "{0, 0.49999999999999994}"
    },
    {
      "_class": "curvePoint",
      "cornerRadius": 0,
      "curveFrom": "{0.77589545014520811, 1}",
      "curveMode": 2,
      "curveTo": "{0.22410454985479189, 1}",
      "hasCurveFrom": true,
      "hasCurveTo": true,
      "point": "{0.5, 1}"
    },
    {
      "_class": "curvePoint",
      "cornerRadius": 0,
      "curveFrom": "{1, 0.22410454985479178}",
      "curveMode": 2,
      "curveTo": "{1, 0.77589545014520811}",
      "hasCurveFrom": true,
      "hasCurveTo": true,
      "point": "{1, 0.49999999999999994}"
    }
  ],
  "resizingConstraint": 63,
  "resizingType": 0,
  "rotation": 0,
  "shouldBreakMaskChain": false
}