{
  "_class": "shapePath",
  "booleanOperation": -1,
  "do_objectID": "62DC3740-607F-42F6-8959-539700184FF1",
  "edited": true,
  "exportOptions": {
    "_class": "exportOptions",
    "do_objectID": "299F1236-9946-41C4-A4A3-1CC10A18709F",
    "exportFormats": [
    ],
    "includedLayerIds": [
    ],
    "layerOptions": 0,
    "shouldTrim": false
  },
  "frame": {
    "_class": "rect",
    "constrainProportions": false,
    "do_objectID": "E4EA100E-7A93-45E7-9081-48CAC680B0AC",
    "height": 4.350999999999999,
    "width": 1,
    "x": 0,
    "y": 0
  },
  "isClosed": false,
  "isFlippedHorizontal": false,
  "isFlippedVertical": false,
  "isLocked": false,
  "isVisible": true,
  "layerListExpandedType": 0,
  "name": "Path",
  "nameIsFixed": false,
  "pointRadiusBehaviour": 1,
  "points": [
    {
      "_class": "curvePoint",
      "cornerRadius": 0,
      "curveFrom": "{0.36100000000000421, 0.21788094690875676}",
      "curveMode": 4,
      "curveTo": "{0, 0}",
      "hasCurveFrom": true,
      "hasCurveTo": false,
      "point": "{0, 0}"
    },
    {
      "_class": "curvePoint",
      "cornerRadius": 0,
      "curveFrom": "{0, 0.6667432774074934}",
      "curveMode": 4,
      "curveTo": "{0.36100000000000421, 0.7821190530912433}",
      "hasCurveFrom": true,
      "hasCurveTo": true,
      "point": "{0, 1}"
    },
    {
      "_class": "curvePoint",
      "cornerRadius": 0,
      "curveFrom": "{0, 0}",
      "curveMode": 4,
      "curveTo": "{0, 0.33325672259250821}",
      "hasCurveFrom": false,
      "hasCurveTo": true,
      "point": "{0, 0}"
    }
  ],
  "resizingConstraint": 63,
  "resizingType": 0,
  "rotation": 0,
  "shouldBreakMaskChain": false
}