{
  "_class": "shapePath",
  "booleanOperation": -1,
  "do_objectID": "2BAE4571-1D12-4780-9C09-21E368430A3E",
  "edited": true,
  "exportOptions": {
    "_class": "exportOptions",
    "do_objectID": "DB9B44F7-CA24-4063-9A7E-5F6C29844875",
    "exportFormats": [
    ],
    "includedLayerIds": [
    ],
    "layerOptions": 0,
    "shouldTrim": false
  },
  "frame": {
    "_class": "rect",
    "constrainProportions": false,
    "do_objectID": "BBC5F7F1-BB7B-41F0-8D9A-5FCEBA772B4A",
    "height": 1,
    "width": 2.393000000000001,
    "x": 0,
    "y": 0
  },
  "isClosed": false,
  "isFlippedHorizontal": false,
  "isFlippedVertical": false,
  "isLocked": false,
  "isVisible": true,
  "layerListExpandedType": 0,
  "name": "Path",
  "nameIsFixed": false,
  "path": {
    "_class": "path",
    "isClosed": false,
    "pointRadiusBehaviour": 1,
    "points": [
      {
        "_class": "curvePoint",
        "cornerRadius": 0,
        "curveFrom": "{0.12703719180944503, -0.090249999999997499}",
        "curveMode": 4,
        "curveTo": "{0, 0.2707499999999925}",
        "hasCurveFrom": true,
        "hasCurveTo": false,
        "point": "{0, 0.2707499999999925}"
      },
      {
        "_class": "curvePoint",
        "cornerRadius": 0,
        "curveFrom": "{0.66652737150020824, 0.2707499999999925}",
        "curveMode": 4,
        "curveTo": "{0.87254492269118578, -0.090249999999997499}",
        "hasCurveFrom": true,
        "hasCurveTo": true,
        "point": "{1, 0.2707499999999925}"
      },
      {
        "_class": "curvePoint",
        "cornerRadius": 0,
        "curveFrom": "{0, 0.2707499999999925}",
        "curveMode": 4,
        "curveTo": "{0.33305474300041654, 0.2707499999999925}",
        "hasCurveFrom": false,
        "hasCurveTo": true,
        "point": "{0, 0.2707499999999925}"
      }
    ]
  },
  "pointRadiusBehaviour": 1,
  "points": [
    {
      "_class": "curvePoint",
      "cornerRadius": 0,
      "curveFrom": "{0.12703719180944503, -0.090249999999997499}",
      "curveMode": 4,
      "curveTo": "{0, 0.2707499999999925}",
      "hasCurveFrom": true,
      "hasCurveTo": false,
      "point": "{0, 0.2707499999999925}"
    },
    {
      "_class": "curvePoint",
      "cornerRadius": 0,
      "curveFrom": "{0.66652737150020824, 0.2707499999999925}",
      "curveMode": 4,
      "curveTo": "{0.87254492269118578, -0.090249999999997499}",
      "hasCurveFrom": true,
      "hasCurveTo": true,
      "point": "{1, 0.2707499999999925}"
    },
    {
      "_class": "curvePoint",
      "cornerRadius": 0,
      "curveFrom": "{0, 0.2707499999999925}",
      "curveMode": 4,
      "curveTo": "{0.33305474300041654, 0.2707499999999925}",
      "hasCurveFrom": false,
      "hasCurveTo": true,
      "point": "{0, 0.2707499999999925}"
    }
  ],
  "resizingConstraint": 63,
  "resizingType": 0,
  "rotation": 0,
  "shouldBreakMaskChain": false
}