{
  "_class": "symbolInstance",
  "do_objectID": "580B233B-9B4E-4990-AFA9-C56250FD861E",
  "exportOptions": {
    "_class": "exportOptions",
    "do_objectID": "2AF03009-2463-4ED3-B16F-5E463E0EFB72",
    "exportFormats": [
    ],
    "includedLayerIds": [
    ],
    "layerOptions": 0,
    "shouldTrim": false
  },
  "frame": {
    "_class": "rect",
    "constrainProportions": false,
    "do_objectID": "DE05AFF0-3F1C-4F73-B253-3964BE66A5A3",
    "height": 117,
    "width": 699,
    "x": 20,
    "y": 140
  },
  "horizontalSpacing": 0,
  "isFlippedHorizontal": false,
  "isFlippedVertical": false,
  "isLocked": false,
  "isVisible": true,
  "layerListExpandedType": 0,
  "name": "Details/Timeline_item Copy 2",
  "nameIsFixed": false,
  "overrideValues": [
    {
      "_class": "overrideValue",
      "do_objectID": "2CED4C6B-C132-41C7-8C0C-6022C6FD6A9E",
      "overrideName": "57CFB7E2-8E39-4293-86B9-81F605792F82_stringValue",
      "value": "Purchased from MediaMarkt"
    }
  ],
  "resizingConstraint": 27,
  "resizingType": 0,
  "rotation": 0,
  "scale": 1,
  "shouldBreakMaskChain": false,
  "style": {
    "_class": "style",
    "do_objectID": "2688E949-E2D4-4D12-A91F-23EF29CE55CD",
    "endDecorationType": 0,
    "miterLimit": 10,
    "startDecorationType": 0
  },
  "symbolID": "01591450-AA22-4309-B558-DD639D09D6C4",
  "verticalSpacing": 0
}