{
  "_class": "shapePath",
  "booleanOperation": 1,
  "do_objectID": "B9397817-34D8-471E-9E56-8ED914A93669",
  "edited": true,
  "exportOptions": {
    "_class": "exportOptions",
    "do_objectID": "50D5DD05-386B-44BE-A90B-8925FC004BB4",
    "exportFormats": [
    ],
    "includedLayerIds": [
    ],
    "layerOptions": 0,
    "shouldTrim": false
  },
  "frame": {
    "_class": "rect",
    "constrainProportions": false,
    "do_objectID": "CBFB0CC1-E66C-40D4-950D-00A83700BEE2",
    "height": 8.124920654296874,
    "width": 8.124920654296874,
    "x": 8.31253967285157,
    "y": 8.31253967285157
  },
  "isClosed": true,
  "isFlippedHorizontal": false,
  "isFlippedVertical": false,
  "isLocked": false,
  "isVisible": true,
  "layerListExpandedType": 0,
  "name": "Shape",
  "nameIsFixed": false,
  "pointRadiusBehaviour": 1,
  "points": [
    {
      "_class": "curvePoint",
      "cornerRadius": 0,
      "curveFrom": "{0.22429906542056086, 1}",
      "curveMode": 2,
      "curveTo": "{0.77570093457943912, 1}",
      "hasCurveFrom": true,
      "hasCurveTo": true,
      "point": "{0.5, 1}"
    },
    {
      "_class": "curvePoint",
      "cornerRadius": 0,
      "curveFrom": "{0, 0.22429906542056033}",
      "curveMode": 2,
      "curveTo": "{0, 0.77570093457943923}",
      "hasCurveFrom": true,
      "hasCurveTo": true,
      "point": "{0, 0.49999999999999978}"
    },
    {
      "_class": "curvePoint",
      "cornerRadius": 0,
      "curveFrom": "{0.77570093457943934, 0}",
      "curveMode": 2,
      "curveTo": "{0.22429906542056066, 0}",
      "hasCurveFrom": true,
      "hasCurveTo": true,
      "point": "{0.5, 0}"
    },
    {
      "_class": "curvePoint",
      "cornerRadius": 0,
      "curveFrom": "{1, 0.77570093457943967}",
      "curveMode": 2,
      "curveTo": "{1, 0.22429906542056074}",
      "hasCurveFrom": true,
      "hasCurveTo": true,
      "point": "{1, 0.50000000000000022}"
    }
  ],
  "resizingConstraint": 63,
  "resizingType": 0,
  "rotation": 0,
  "shouldBreakMaskChain": false
}