{
  "_class": "symbolInstance",
  "do_objectID": "65967E4C-034B-49B8-9F50-AE1BD97C3F49",
  "exportOptions": {
    "_class": "exportOptions",
    "do_objectID": "6B838479-FA4C-451C-9893-C25F31938E03",
    "exportFormats": [
    ],
    "includedLayerIds": [
    ],
    "layerOptions": 0,
    "shouldTrim": false
  },
  "frame": {
    "_class": "rect",
    "constrainProportions": false,
    "do_objectID": "5FD8233D-8467-4EC3-8C77-3974FDCF109F",
    "height": 48,
    "width": 64,
    "x": 256,
    "y": 0
  },
  "horizontalSpacing": 0,
  "isFlippedHorizontal": false,
  "isFlippedVertical": false,
  "isLocked": false,
  "isVisible": true,
  "layerListExpandedType": 0,
  "name": "Nav_Button Copy 4",
  "nameIsFixed": false,
  "overrideValues": [
    {
      "_class": "overrideValue",
      "do_objectID": "F39A5DCC-EF50-43C6-A05E-1FB8D69A9749",
      "overrideName": "2DA2CC86-2EA8-4D18-9979-4775614F4D70_symbolID",
      "value": "B091DAD6-36F0-4A82-A3D3-73C1E573FD7D"
    },
    {
      "_class": "overrideValue",
      "do_objectID": "31A8CAB9-4A8E-4C98-932C-E8165AEE85A6",
      "overrideName": "83637734-A485-4C40-B28E-AEB9E0456A7C_stringValue",
      "value": "Setting"
    }
  ],
  "resizingConstraint": 13,
  "resizingType": 0,
  "rotation": 0,
  "scale": 1,
  "shouldBreakMaskChain": false,
  "style": {
    "_class": "style",
    "contextSettings": {
      "_class": "graphicsContextSettings",
      "blendMode": 0,
      "do_objectID": "5F137386-CB2B-440E-ABFB-8233E7938D45",
      "opacity": 0.5
    },
    "do_objectID": "24FE6350-B0F8-4663-9453-CF3DFEF02F05",
    "endDecorationType": 0,
    "miterLimit": 10,
    "startDecorationType": 0
  },
  "symbolID": "F5B67219-D825-4234-AB19-A0A0A8C3D675",
  "verticalSpacing": 0
}