{
  "_class": "shapeGroup",
  "clippingMaskMode": 0,
  "do_objectID": "C2DE4167-BABB-470E-BCF2-DD77BCAF0B13",
  "exportOptions": {
    "_class": "exportOptions",
    "do_objectID": "8431228D-0949-4587-9990-E0F4ECC04F73",
    "exportFormats": [
    ],
    "includedLayerIds": [
    ],
    "layerOptions": 0,
    "shouldTrim": false
  },
  "frame": {
    "_class": "rect",
    "constrainProportions": false,
    "do_objectID": "38B09219-35BA-4FE8-96FA-830FEF1BDEBC",
    "height": 40,
    "width": 288,
    "x": 0,
    "y": 0
  },
  "hasClickThrough": false,
  "hasClippingMask": false,
  "isFlippedHorizontal": false,
  "isFlippedVertical": false,
  "isLocked": false,
  "isVisible": true,
  "layerListExpandedType": 0,
  "layers": [
    {
      "class": "rectangle",
      "id": "E8E1FFEB-76D0-489B-A13F-91E2887F8914"
    }
  ],
  "name": "Rectangle 4 Copy",
  "nameIsFixed": false,
  "resizingConstraint": 18,
  "resizingType": 0,
  "rotation": 0,
  "shouldBreakMaskChain": false,
  "style": {
    "_class": "style",
    "borders": [
      {
        "_class": "border",
        "color": {
          "_class": "color",
          "alpha": 1,
          "blue": 0.592,
          "green": 0.592,
          "red": 0.592
        },
        "fillType": 0,
        "isEnabled": false,
        "position": 2,
        "thickness": 1
      }
    ],
    "contextSettings": {
      "_class": "graphicsContextSettings",
      "blendMode": 0,
      "do_objectID": "56CFD059-FE0A-477E-AC37-CA22BDA9C945",
      "opacity": 0.5
    },
    "do_objectID": "B6BCCC45-6EC9-49C2-B2A9-B21FDD12FE34",
    "endDecorationType": 0,
    "fills": [
      {
        "_class": "fill",
        "color": {
          "_class": "color",
          "alpha": 1,
          "blue": 0.9450980392156862,
          "green": 0.9411764705882353,
          "red": 0.9254901960784314
        },
        "fillType": 0,
        "isEnabled": true,
        "noiseIndex": 0,
        "noiseIntensity": 0,
        "patternFillType": 1,
        "patternTileScale": 1
      }
    ],
    "miterLimit": 10,
    "startDecorationType": 0
  },
  "windingRule": 1
}